<?xml version="1.0" encoding="UTF-8"?><rdf:RDF xmlns:rdf="http://www.w3.org/1999/02/22-rdf-syntax-ns#" xmlns:cc="http://creativecommons.org/ns#" xmlns:dc="http://purl.org/dc/elements/1.1/" xmlns:dcterms="http://purl.org/dc/terms/" xmlns:doap="http://usefulinc.com/ns/doap#" xmlns:edm="http://www.europeana.eu/schemas/edm/" xmlns:foaf="http://xmlns.com/foaf/0.1/" xmlns:ore="http://www.openarchives.org/ore/terms/" xmlns:owl="http://www.w3.org/2002/07/owl#" xmlns:rdaGr2="http://rdvocab.info/ElementsGr2/" xmlns:rdfs="http://www.w3.org/2000/01/rdf-schema#" xmlns:skos="http://www.w3.org/2004/02/skos/core#" xmlns:svcs="http://rdfs.org/sioc/services#" xmlns:wgs84_pos="http://www.w3.org/2003/01/geo/wgs84_pos#" xmlns:xsi="http://www.w3.org/2001/XMLSchema-instance"><edm:ProvidedCHO rdf:about="https://d.lib.ncsu.edu/collections/catalog/0007398"><dc:subject>Alumni and alumnae</dc:subject><dc:subject rdf:resource="1b3a1bbe-096e-4a26-ba81-8e07823cd36e"/><dc:title>Herman W. "Pop" Taylor, receiving Watauga Medal from Chancellor Joab Thomas</dc:title><dc:subject rdf:resource="bd04ceae-ccfc-47a1-9337-2ece5dbf9bcf"/><dc:subject>People</dc:subject><dcterms:created>1978</dcterms:created><dc:subject rdf:resource="3cb38b48-526a-4e10-8c8c-1e8fec7c6147"/><dc:subject rdf:resource="82843544-a20a-47b7-91cb-2267caf9fe17"/><dc:subject rdf:resource="d9abddf6-d363-487f-820a-b7498ceca066"/><dc:subject>College presidents</dc:subject><edm:hasType rdf:resource="http://schema.org/CreativeWork"/><dcterms:isPartOf>https://d.lib.ncsu.edu/collections/catalog?f%5Bispartof_facet%5D%5B%5D=University+Archives+Photographs</dcterms:isPartOf><dc:subject rdf:resource="7901a433-2b3e-4685-bf83-abfcebba9a78"/></edm:ProvidedCHO><ore:Aggregation rdf:about="https://d.lib.ncsu.edu/collections/catalog/0007398#Aggregation"><edm:provider>NC State University Libraries</edm:provider><edm:dataProvider>NC State University Libraries</edm:dataProvider><edm:aggregatedCHO rdf:resource="https://d.lib.ncsu.edu/collections/catalog/0007398"/><edm:object rdf:resource="https://iiif.lib.ncsu.edu/iiif/0007398/full/350,/0/default.jpg"/><edm:isShownBy rdf:resource="https://iiif.lib.ncsu.edu/iiif/0007398/full/350,/0/default.jpg"/><edm:isShownAt rdf:resource="https://d.lib.ncsu.edu/collections/catalog/0007398"/></ore:Aggregation><skos:Concept rdf:about="1b3a1bbe-096e-4a26-ba81-8e07823cd36e"><skos:prefLabel>Alumni and alumnae</skos:prefLabel></skos:Concept><skos:Concept rdf:about="bd04ceae-ccfc-47a1-9337-2ece5dbf9bcf"><skos:prefLabel>People</skos:prefLabel></skos:Concept><edm:Agent rdf:about="3cb38b48-526a-4e10-8c8c-1e8fec7c6147"><rdaGr2:birthDate>1900</rdaGr2:birthDate><rdaGr2:deathDate>1988</rdaGr2:deathDate><skos:prefLabel>Herman Ward, Taylor</skos:prefLabel><skos:prefLabel>Taylor, Herman Ward, 1900-1988</skos:prefLabel></edm:Agent><skos:Concept rdf:about="82843544-a20a-47b7-91cb-2267caf9fe17"><skos:prefLabel>College presidents</skos:prefLabel></skos:Concept><edm:Agent rdf:about="d9abddf6-d363-487f-820a-b7498ceca066"><rdaGr2:birthDate>1933</rdaGr2:birthDate><rdaGr2:deathDate>2014</rdaGr2:deathDate><skos:prefLabel>Joab Langston, Thomas</skos:prefLabel><skos:prefLabel>Thomas, Joab L.</skos:prefLabel></edm:Agent><foaf:Organization rdf:about="7901a433-2b3e-4685-bf83-abfcebba9a78"><skos:prefLabel>North Carolina State University -- Administration</skos:prefLabel></foaf:Organization></rdf:RDF>