<?xml version="1.0" encoding="UTF-8"?><rdf:RDF xmlns:rdf="http://www.w3.org/1999/02/22-rdf-syntax-ns#" xmlns:cc="http://creativecommons.org/ns#" xmlns:dc="http://purl.org/dc/elements/1.1/" xmlns:dcterms="http://purl.org/dc/terms/" xmlns:doap="http://usefulinc.com/ns/doap#" xmlns:edm="http://www.europeana.eu/schemas/edm/" xmlns:foaf="http://xmlns.com/foaf/0.1/" xmlns:ore="http://www.openarchives.org/ore/terms/" xmlns:owl="http://www.w3.org/2002/07/owl#" xmlns:rdaGr2="http://rdvocab.info/ElementsGr2/" xmlns:rdfs="http://www.w3.org/2000/01/rdf-schema#" xmlns:skos="http://www.w3.org/2004/02/skos/core#" xmlns:svcs="http://rdfs.org/sioc/services#" xmlns:wgs84_pos="http://www.w3.org/2003/01/geo/wgs84_pos#" xmlns:xsi="http://www.w3.org/2001/XMLSchema-instance"><edm:ProvidedCHO rdf:about="https://d.lib.ncsu.edu/collections/catalog/0001233"><dcterms:created>1942</dcterms:created><dc:subject rdf:resource="e3f37c67-7dde-4216-af26-1c1c2c638ca1"/><dc:title>U.S. Army Hospital Ship Larkspur, the entire cost of which -- $4 million -- was underwritten by war bond subscriptions from the North Carolina Federation of Home Demonstration Clubs and the North Carolina Nurses Association.</dc:title><dc:subject>Hospital ships</dc:subject><dc:subject>Home demonstration work</dc:subject><dc:subject rdf:resource="ca92a4c6-a128-4dab-8bf4-54ed8196ec7f"/><dc:subject rdf:resource="2028cd17-8e53-455d-9420-782949dcae30"/><dcterms:isPartOf>https://d.lib.ncsu.edu/collections/catalog?f%5Bispartof_facet%5D%5B%5D=Green+%27N%27+Growing</dcterms:isPartOf><edm:hasType rdf:resource="http://schema.org/CreativeWork"/><dc:subject rdf:resource="1de0ba68-53e1-46c1-928f-a84b5cbfdb0c"/><dcterms:isPartOf>https://d.lib.ncsu.edu/collections/catalog?f%5Bispartof_facet%5D%5B%5D=University+Archives+Photographs</dcterms:isPartOf><dc:subject>Community and Extension</dc:subject><dc:subject>World War, 1939-1945</dc:subject><dc:description>Ship shown in port at Charleston, South Carolina.</dc:description></edm:ProvidedCHO><ore:Aggregation rdf:about="https://d.lib.ncsu.edu/collections/catalog/0001233#Aggregation"><edm:provider>NC State University Libraries</edm:provider><edm:dataProvider>NC State University Libraries</edm:dataProvider><edm:aggregatedCHO rdf:resource="https://d.lib.ncsu.edu/collections/catalog/0001233"/><edm:isShownAt rdf:resource="https://d.lib.ncsu.edu/collections/catalog/0001233"/><edm:object rdf:resource="https://iiif.lib.ncsu.edu/iiif/0001233/full/350,/0/default.jpg"/><edm:isShownBy rdf:resource="https://iiif.lib.ncsu.edu/iiif/0001233/full/350,/0/default.jpg"/></ore:Aggregation><skos:Concept rdf:about="e3f37c67-7dde-4216-af26-1c1c2c638ca1"><skos:prefLabel>Community and Extension</skos:prefLabel></skos:Concept><skos:Concept rdf:about="ca92a4c6-a128-4dab-8bf4-54ed8196ec7f"><skos:prefLabel>World War, 1939-1945</skos:prefLabel></skos:Concept><skos:Concept rdf:about="2028cd17-8e53-455d-9420-782949dcae30"><skos:prefLabel>Hospital ships</skos:prefLabel></skos:Concept><skos:Concept rdf:about="1de0ba68-53e1-46c1-928f-a84b5cbfdb0c"><skos:prefLabel>Home demonstration work</skos:prefLabel></skos:Concept></rdf:RDF>