<?xml version="1.0" encoding="UTF-8"?><rdf:RDF xmlns:rdf="http://www.w3.org/1999/02/22-rdf-syntax-ns#" xmlns:cc="http://creativecommons.org/ns#" xmlns:dc="http://purl.org/dc/elements/1.1/" xmlns:dcterms="http://purl.org/dc/terms/" xmlns:doap="http://usefulinc.com/ns/doap#" xmlns:edm="http://www.europeana.eu/schemas/edm/" xmlns:foaf="http://xmlns.com/foaf/0.1/" xmlns:ore="http://www.openarchives.org/ore/terms/" xmlns:owl="http://www.w3.org/2002/07/owl#" xmlns:rdaGr2="http://rdvocab.info/ElementsGr2/" xmlns:rdfs="http://www.w3.org/2000/01/rdf-schema#" xmlns:skos="http://www.w3.org/2004/02/skos/core#" xmlns:svcs="http://rdfs.org/sioc/services#" xmlns:wgs84_pos="http://www.w3.org/2003/01/geo/wgs84_pos#" xmlns:xsi="http://www.w3.org/2001/XMLSchema-instance"><edm:ProvidedCHO rdf:about="https://d.lib.ncsu.edu/collections/catalog/0050199"><dc:subject>Agricultural extension workers</dc:subject><dc:subject>Community and Extension</dc:subject><edm:hasType rdf:resource="http://schema.org/CreativeWork"/><dcterms:isPartOf>https://d.lib.ncsu.edu/collections/catalog?f%5Bispartof_facet%5D%5B%5D=University+Archives+Photographs</dcterms:isPartOf><dc:subject rdf:resource="c00d6f70-de8f-414b-a6c8-fdfdf1790852"/><dc:subject rdf:resource="cc88ad90-79ed-437a-bed5-b0b0da7350cb"/><dc:subject rdf:resource="30d2fd93-1af1-4089-b408-f095da774825"/><dc:title>Mr. J. F. Eagles probably the first demonstrator signed by County Agent J. A. Butler</dc:title><dc:description>Mr. J. F. Eagles, Statesville, N.C., probably the first demonstrator signed by County Agent J. A. Butler, November 20, 1907. James A. Butler was appointed the first county agent in North Carolina, November 18, 1907. He arranged the first Cooperative Extension demonstration with J. F. Eagles of Statesville, November 20, 1907</dc:description><dcterms:isPartOf>https://d.lib.ncsu.edu/collections/catalog?f%5Bispartof_facet%5D%5B%5D=Living+Off+the+Land</dcterms:isPartOf><dcterms:created>1907-11-20</dcterms:created><dc:subject rdf:resource="863b1a74-5cab-4d0c-9919-4ad5160f6012"/><dc:language>eng</dc:language><dc:subject>Agriculture</dc:subject><dc:subject rdf:resource="7cfaaa81-2c76-44a9-9c36-ef3c0e4d239a"/><dc:subject rdf:resource="1df9dc64-8742-4d4a-95cb-c64351b9a100"/></edm:ProvidedCHO><ore:Aggregation rdf:about="https://d.lib.ncsu.edu/collections/catalog/0050199#Aggregation"><edm:provider>NC State University Libraries</edm:provider><edm:dataProvider>NC State University Libraries</edm:dataProvider><edm:aggregatedCHO rdf:resource="https://d.lib.ncsu.edu/collections/catalog/0050199"/><edm:isShownAt rdf:resource="https://d.lib.ncsu.edu/collections/catalog/0050199"/><edm:isShownBy rdf:resource="https://iiif.lib.ncsu.edu/iiif/0050199/full/350,/0/default.jpg"/><edm:object rdf:resource="https://iiif.lib.ncsu.edu/iiif/0050199/full/350,/0/default.jpg"/></ore:Aggregation><edm:Place rdf:about="c00d6f70-de8f-414b-a6c8-fdfdf1790852"><wgs84_pos:lat>35.7826363</wgs84_pos:lat><wgs84_pos:long>-80.8872959</wgs84_pos:long><skos:prefLabel>Statesville (N.C.)</skos:prefLabel></edm:Place><foaf:Organization rdf:about="cc88ad90-79ed-437a-bed5-b0b0da7350cb"><skos:note>North Carolina Agricultural Extension Service is a cooperative service between North Carolina State University, North Carolina Agricultural and Technical University, and the U.S. Dept. of Agriculture; located on campus of N.C. State University.</skos:note><skos:prefLabel>North Carolina Cooperative Extension Service</skos:prefLabel></foaf:Organization><skos:Concept rdf:about="30d2fd93-1af1-4089-b408-f095da774825"><skos:prefLabel>Agriculture</skos:prefLabel></skos:Concept><skos:Concept rdf:about="863b1a74-5cab-4d0c-9919-4ad5160f6012"><skos:prefLabel>Community and Extension</skos:prefLabel></skos:Concept><skos:Concept rdf:about="7cfaaa81-2c76-44a9-9c36-ef3c0e4d239a"><skos:prefLabel>Agricultural extension workers</skos:prefLabel></skos:Concept><edm:Agent rdf:about="1df9dc64-8742-4d4a-95cb-c64351b9a100"><skos:prefLabel>Eagles, J.F.</skos:prefLabel></edm:Agent></rdf:RDF>